import_zig/__init__.py
import_zig/build.zig
import_zig/zig_ext/c.h
import_zig/zig_ext/py_utils.zig
import_zig/zig_ext/zig_ext.zig
import_zig-0.15.1.dist-info/licenses/LICENSE
import_zig-0.15.1.dist-info/METADATA
import_zig-0.15.1.dist-info/WHEEL
import_zig-0.15.1.dist-info/top_level.txt
import_zig-0.15.1.dist-info/RECORD
