Metadata-Version: 2.4
Name: import_zig
Version: 0.15.1
Summary: Compile and import Zig functions at runtime without building a package
Author: Felix Graßl
License: MIT
Project-URL: Homepage, https://github.com/ffelixg/import_zig
Project-URL: Issues, https://github.com/ffelixg/import_zig/issues
Keywords: zig,ziglang,import,compile
Classifier: License :: OSI Approved :: MIT License
Classifier: Programming Language :: Python
Classifier: Programming Language :: Python :: 3
Requires-Python: >=3.10
License-File: LICENSE
Requires-Dist: ziglang==0.15.1
Dynamic: license-file
